LICENSE
README.md
setup.cfg
setup.py
roadwork/__init__.py
roadwork/version.py
roadwork.egg-info/PKG-INFO
roadwork.egg-info/SOURCES.txt
roadwork.egg-info/dependency_links.txt
roadwork.egg-info/not-zip-safe
roadwork.egg-info/requires.txt
roadwork.egg-info/top_level.txt
roadwork/client/__init__.py
roadwork/client/client.py
roadwork/client/client_dapr.py
roadwork/client/ray_environment.py
roadwork/client/rw_actor_interface.py
roadwork/grpc/__init__.py
roadwork/grpc/serializer.py
roadwork/grpc/unserializer.py
roadwork/json/__init__.py
roadwork/json/serializer.py
roadwork/json/unserializer.py
roadwork/proto/__init__.py
roadwork/proto/roadwork_pb2.py
roadwork/proto/roadwork_pb2_grpc.py
roadwork/server/__init__.py
roadwork/server/actor_interface.py
roadwork/server/base_server.py
roadwork/utils/__init__.py
roadwork/utils/gym_parser.py
roadwork/utils/proto_util.py